odoo/addons/sm_member_geolocation/__init__.py
odoo/addons/sm_member_geolocation/__manifest__.py
odoo/addons/sm_member_geolocation/models/__init__.py
odoo/addons/sm_member_geolocation/models/models_sm_geolocation_cron.py
odoo/addons/sm_member_geolocation/models/models_sm_member.py
odoo/addons/sm_member_geolocation/models/models_sm_members_zone.py
odoo/addons/sm_member_geolocation/security/ir.model.access.csv
odoo/addons/sm_member_geolocation/views/views_cron.xml
odoo/addons/sm_member_geolocation/views/views_members.xml
odoo/addons/sm_member_geolocation/views/views_members_zone.xml
odoo12_addon_sm_member_geolocation-12.0.0.0.6.dist-info/METADATA
odoo12_addon_sm_member_geolocation-12.0.0.0.6.dist-info/WHEEL
odoo12_addon_sm_member_geolocation-12.0.0.0.6.dist-info/top_level.txt
odoo12_addon_sm_member_geolocation-12.0.0.0.6.dist-info/RECORD
